expi_skel/__init__.py
expi_skel/expi.json
expi_skel/vi/EXPISKEL.2665093.vi
expi_skel-0.5.5.dist-info/LICENSE.txt
expi_skel-0.5.5.dist-info/METADATA
expi_skel-0.5.5.dist-info/WHEEL
expi_skel-0.5.5.dist-info/top_level.txt
expi_skel-0.5.5.dist-info/RECORD
