Metadata-Version: 2.1
Name: expi-skel
Version: 0.5.5
Summary: A package template for use with the Extender Package Index.
Home-page: https://2665093.ca
Author: 2665093 Ontario Inc.
Author-email: chris@2665093.ca
License: UNKNOWN
Download-URL: https://expi.2665093.ca/2665093/expi_skel
Keywords: Orchid,Extender,Sage 300,Automation
Platform: UNKNOWN
Classifier: Development Status :: 5 - Production/Stable
Classifier: Environment :: Win32 (MS Windows)
Classifier: Intended Audience :: End Users/Desktop
Classifier: License :: Other/Proprietary License
Classifier: Operating System :: Microsoft :: Windows
Classifier: Programming Language :: Python :: 3.4
Requires-Dist: extools
